dash_emoji_mart/DashEmojiMart.py
dash_emoji_mart/__init__.py
dash_emoji_mart/_imports_.py
dash_emoji_mart/dash_emoji_mart.min.js
dash_emoji_mart/dash_emoji_mart.min.js.map
dash_emoji_mart/metadata.json
dash_emoji_mart/package-info.json
dash_emoji_mart-0.0.3.dist-info/LICENSE
dash_emoji_mart-0.0.3.dist-info/METADATA
dash_emoji_mart-0.0.3.dist-info/WHEEL
dash_emoji_mart-0.0.3.dist-info/top_level.txt
dash_emoji_mart-0.0.3.dist-info/RECORD
