Metadata-Version: 2.1
Name: dash-emoji-mart
Version: 0.0.3
Summary: emoji-mart for dash
Author: pip install python <pipinstallpython@gmail.com>
License: MIT
Classifier: Framework :: Dash
License-File: LICENSE
